cookiepy/__init__.py
cookiepy/cli.py
cookiepy/cookiepy.py
cookiepy/files.py
cookiepy/generate_tfrecords.py
cookiepy/od_methods.py
cookiepy/recipe.py
cookiepy/tf_models.py
cookiepy/xml_to_csv.py
cookiepy-0.9.5.dist-info/AUTHORS.rst
cookiepy-0.9.5.dist-info/LICENSE
cookiepy-0.9.5.dist-info/METADATA
cookiepy-0.9.5.dist-info/WHEEL
cookiepy-0.9.5.dist-info/entry_points.txt
cookiepy-0.9.5.dist-info/top_level.txt
cookiepy-0.9.5.dist-info/RECORD
