Metadata-Version: 2.1
Name: cookiepy
Version: 0.9.5
Summary: Python Boilerplate for Python package.
Home-page: https://github.com/SpiralOutDoEu/cookiepy
Author: Nikos Koumbakis
Author-email: n.koumbakis@gmail.com
License: MIT license
Keywords: cookiepy
Platform: UNKNOWN
Classifier: Development Status :: 2 - Pre-Alpha
Classifier: Intended Audience :: Developers
Classifier: License :: OSI Approved :: MIT License
Classifier: Natural Language :: English
Classifier: Programming Language :: Python :: 3
Classifier: Programming Language :: Python :: 3.6
Classifier: Programming Language :: Python :: 3.7
Requires-Python: >=2.7, !=3.0.*, !=3.1.*, !=3.2.*, !=3.3.*, !=3.4.*
Requires-Dist: Click (>=7.0)
Requires-Dist: numpy
Requires-Dist: pandas
Requires-Dist: pillow
Requires-Dist: tensorflow
Requires-Dist: dulwich
